plasmaboundaries/__init__.py
plasmaboundaries/magnetic_flux.py
plasmaboundaries/model.py
plasmaboundaries/parameters.py
plasmaboundaries-0.1.8.data/data/LICENSE.txt
tests/__init__.py
tests/test_model.py
plasmaboundaries-0.1.8.dist-info/LICENSE.txt
plasmaboundaries-0.1.8.dist-info/METADATA
plasmaboundaries-0.1.8.dist-info/WHEEL
plasmaboundaries-0.1.8.dist-info/top_level.txt
plasmaboundaries-0.1.8.dist-info/zip-safe
plasmaboundaries-0.1.8.dist-info/RECORD
