Metadata-Version: 2.1
Name: plasmaboundaries
Version: 0.1.8
Summary: Determine plasma flux functions for various plasma parameters and plasma configurations
Home-page: https://github.com/RemiTheWarrior/plasma-boundaries
Author: Remi Delaporte-Mathurin
Author-email: rdelaportemathurin@gmail.com
License: UNKNOWN
Platform: UNKNOWN
Classifier: Programming Language :: Python :: 3
Classifier: License :: OSI Approved :: MIT License
Classifier: Operating System :: OS Independent
Requires-Dist: matplotlib
Requires-Dist: scipy
Requires-Dist: numpy
Requires-Dist: sympy
